cfpsec/__init__.py
cfpsec/cfpsec.py
cfpsec-1.5.data/scripts/cfpsec.py
cfpsec-1.5.dist-info/LICENSE
cfpsec-1.5.dist-info/METADATA
cfpsec-1.5.dist-info/WHEEL
cfpsec-1.5.dist-info/top_level.txt
cfpsec-1.5.dist-info/RECORD
