Metadata-Version: 2.1
Name: cfpsec
Version: 1.5
Summary: CFPsec is a client program that retrieves the list of Call For Papers or/and upcoming Hacking/Security Conferences based on cfptime.org website.
Home-page: https://github.com/alexandreborges/cfpsec
Author: Alexandre Borges
Author-email: reverseexploit@proton.me
License: GNU GPL v3.0
Classifier: Operating System :: OS Independent
Classifier: License :: OSI Approved :: GNU General Public License v3 or later (GPLv3+)
Classifier: Programming Language :: Python :: 3
License-File: LICENSE
Requires-Dist: colorama
Requires-Dist: requests
Requires-Dist: simplejson
